{
  "url": "https://pddikti.kemdiktisaintek.go.id/detail-prodi/S-a8QmsV7eokDa6jijCMAmny8Seceh3xq7ko5YlGrM4qHlix7C4tOur33-rNsyCT68Ggqw==",
  "profile": {
    "Kode": "54101",
    "Biaya Kuliah": "Rp -",
    "Tanggal Berdiri": "2 Januari 2004",
    "Akreditasi": "Unggul",
    "Akreditasi Internasional": "-",
    "Rasio Dosen : Mahasiswa": "-",
    "Rasio Diterima : Pendaftar": "-",
    "SK Selenggara": "13111/D/T/K-VII/2012",
    "Tanggal SK Selenggara": "1 Oktober 2012",
    "nama_pt": "Universitas Muhammadiyah Malang",
    "nama_prodi": "S2 Agribisnis",
    "Kontak": [
      "0341-562124"
    ]
  },
  "dosen": {
    "Genap 2025": [
      {
        "No": "1",
        "Nama": "UNTUNG SANTOSO",
        "NIDN": "0008116301",
        "NUPTK": "0440741642130083",
        "Pendidikan": "S3",
        "Status": "Aktif",
        "Ikatan Kerja": "Dosen Tetap"
      },
      {
        "No": "2",
        "Nama": "ERNY ISHARTATI",
        "NIDN": "0709056401",
        "NUPTK": "4841742643230072",
        "Pendidikan": "S3",
        "Status": "Aktif",
        "Ikatan Kerja": "Dosen Tetap"
      },
      {
        "No": "3",
        "Nama": "SUTAWI",
        "NIDN": "0022046501",
        "NUPTK": "7754743644130072",
        "Pendidikan": "S3",
        "Status": "Aktif",
        "Ikatan Kerja": "Dosen Tetap"
      },
      {
        "No": "4",
        "Nama": "FATIMAH NURSANDI",
        "NIDN": "0029016602",
        "NUPTK": "8461744645230052",
        "Pendidikan": "S3",
        "Status": "Aktif",
        "Ikatan Kerja": "Dosen Tetap"
      },
      {
        "No": "5",
        "Nama": "ANAS TAIN",
        "NIDN": "0021026602",
        "NUPTK": "5553744645130052",
        "Pendidikan": "S3",
        "Status": "Aktif",
        "Ikatan Kerja": "Dosen Tetap"
      }
    ],
    "Gasal 2025": [
      {
        "No": "1",
        "Nama": "UNTUNG SANTOSO",
        "NIDN": "0008116301",
        "NUPTK": "0440741642130083",
        "Pendidikan": "S3",
        "Status": "Aktif",
        "Ikatan Kerja": "Dosen Tetap"
      },
      {
        "No": "2",
        "Nama": "ERNY ISHARTATI",
        "NIDN": "0709056401",
        "NUPTK": "4841742643230072",
        "Pendidikan": "S3",
        "Status": "Aktif",
        "Ikatan Kerja": "Dosen Tetap"
      },
      {
        "No": "3",
        "Nama": "SUTAWI",
        "NIDN": "0022046501",
        "NUPTK": "7754743644130072",
        "Pendidikan": "S3",
        "Status": "Aktif",
        "Ikatan Kerja": "Dosen Tetap"
      },
      {
        "No": "4",
        "Nama": "FATIMAH NURSANDI",
        "NIDN": "0029016602",
        "NUPTK": "8461744645230052",
        "Pendidikan": "S3",
        "Status": "Aktif",
        "Ikatan Kerja": "Dosen Tetap"
      },
      {
        "No": "5",
        "Nama": "ANAS TAIN",
        "NIDN": "0021026602",
        "NUPTK": "5553744645130052",
        "Pendidikan": "S3",
        "Status": "Aktif",
        "Ikatan Kerja": "Dosen Tetap"
      }
    ],
    "Genap 2024": [
      {
        "No": "1",
        "Nama": "UNTUNG SANTOSO",
        "NIDN": "0008116301",
        "NUPTK": "0440741642130083",
        "Pendidikan": "S3",
        "Status": "Aktif",
        "Ikatan Kerja": "Dosen Tetap"
      },
      {
        "No": "2",
        "Nama": "ERNY ISHARTATI",
        "NIDN": "0709056401",
        "NUPTK": "4841742643230072",
        "Pendidikan": "S3",
        "Status": "Aktif",
        "Ikatan Kerja": "Dosen Tetap"
      },
      {
        "No": "3",
        "Nama": "SUTAWI",
        "NIDN": "0022046501",
        "NUPTK": "7754743644130072",
        "Pendidikan": "S3",
        "Status": "Aktif",
        "Ikatan Kerja": "Dosen Tetap"
      },
      {
        "No": "4",
        "Nama": "FATIMAH NURSANDI",
        "NIDN": "0029016602",
        "NUPTK": "8461744645230052",
        "Pendidikan": "S3",
        "Status": "Aktif",
        "Ikatan Kerja": "Dosen Tetap"
      },
      {
        "No": "5",
        "Nama": "ANAS TAIN",
        "NIDN": "0021026602",
        "NUPTK": "5553744645130052",
        "Pendidikan": "S3",
        "Status": "Aktif",
        "Ikatan Kerja": "Dosen Tetap"
      }
    ],
    "Gasal 2024": [
      {
        "No": "1",
        "Nama": "UNTUNG SANTOSO",
        "NIDN": "0008116301",
        "NUPTK": "0440741642130083",
        "Pendidikan": "S3",
        "Status": "Aktif",
        "Ikatan Kerja": "Dosen Tetap"
      },
      {
        "No": "2",
        "Nama": "ERNY ISHARTATI",
        "NIDN": "0709056401",
        "NUPTK": "4841742643230072",
        "Pendidikan": "S3",
        "Status": "Aktif",
        "Ikatan Kerja": "Dosen Tetap"
      },
      {
        "No": "3",
        "Nama": "SUTAWI",
        "NIDN": "0022046501",
        "NUPTK": "7754743644130072",
        "Pendidikan": "S3",
        "Status": "Aktif",
        "Ikatan Kerja": "Dosen Tetap"
      },
      {
        "No": "4",
        "Nama": "FATIMAH NURSANDI",
        "NIDN": "0029016602",
        "NUPTK": "8461744645230052",
        "Pendidikan": "S3",
        "Status": "Aktif",
        "Ikatan Kerja": "Dosen Tetap"
      },
      {
        "No": "5",
        "Nama": "ANAS TAIN",
        "NIDN": "0021026602",
        "NUPTK": "5553744645130052",
        "Pendidikan": "S3",
        "Status": "Aktif",
        "Ikatan Kerja": "Dosen Tetap"
      }
    ],
    "Genap 2023": [
      {
        "No": "1",
        "Nama": "UNTUNG SANTOSO",
        "NIDN": "0008116301",
        "NUPTK": "0440741642130083",
        "Pendidikan": "S3",
        "Status": "Aktif",
        "Ikatan Kerja": "Dosen Tetap"
      },
      {
        "No": "2",
        "Nama": "ERNY ISHARTATI",
        "NIDN": "0709056401",
        "NUPTK": "4841742643230072",
        "Pendidikan": "S3",
        "Status": "Aktif",
        "Ikatan Kerja": "Dosen Tetap"
      },
      {
        "No": "3",
        "Nama": "SUTAWI",
        "NIDN": "0022046501",
        "NUPTK": "7754743644130072",
        "Pendidikan": "S3",
        "Status": "Aktif",
        "Ikatan Kerja": "Dosen Tetap"
      },
      {
        "No": "4",
        "Nama": "FATIMAH NURSANDI",
        "NIDN": "0029016602",
        "NUPTK": "8461744645230052",
        "Pendidikan": "S3",
        "Status": "Aktif",
        "Ikatan Kerja": "Dosen Tetap"
      },
      {
        "No": "5",
        "Nama": "ANAS TAIN",
        "NIDN": "0021026602",
        "NUPTK": "5553744645130052",
        "Pendidikan": "S3",
        "Status": "Aktif",
        "Ikatan Kerja": "Dosen Tetap"
      }
    ],
    "Gasal 2023": [
      {
        "No": "1",
        "Nama": "UNTUNG SANTOSO",
        "NIDN": "0008116301",
        "NUPTK": "0440741642130083",
        "Pendidikan": "S3",
        "Status": "Aktif",
        "Ikatan Kerja": "Dosen Tetap"
      },
      {
        "No": "2",
        "Nama": "ERNY ISHARTATI",
        "NIDN": "0709056401",
        "NUPTK": "4841742643230072",
        "Pendidikan": "S3",
        "Status": "Aktif",
        "Ikatan Kerja": "Dosen Tetap"
      },
      {
        "No": "3",
        "Nama": "SUTAWI",
        "NIDN": "0022046501",
        "NUPTK": "7754743644130072",
        "Pendidikan": "S3",
        "Status": "Aktif",
        "Ikatan Kerja": "Dosen Tetap"
      },
      {
        "No": "4",
        "Nama": "FATIMAH NURSANDI",
        "NIDN": "0029016602",
        "NUPTK": "8461744645230052",
        "Pendidikan": "S3",
        "Status": "Aktif",
        "Ikatan Kerja": "Dosen Tetap"
      },
      {
        "No": "5",
        "Nama": "ANAS TAIN",
        "NIDN": "0021026602",
        "NUPTK": "5553744645130052",
        "Pendidikan": "S3",
        "Status": "Aktif",
        "Ikatan Kerja": "Dosen Tetap"
      }
    ]
  },
  "mahasiswa": [
    {
      "semester": "2025/2026 Genap",
      "jumlah_mahasiswa": "0"
    },
    {
      "semester": "2025/2026 Ganjil",
      "jumlah_mahasiswa": "45"
    },
    {
      "semester": "2024/2025 Genap",
      "jumlah_mahasiswa": "45"
    },
    {
      "semester": "2024/2025 Ganjil",
      "jumlah_mahasiswa": "41"
    },
    {
      "semester": "2023/2024 Genap",
      "jumlah_mahasiswa": "43"
    },
    {
      "semester": "2023/2024 Ganjil",
      "jumlah_mahasiswa": "44"
    },
    {
      "semester": "2022/2023 Genap",
      "jumlah_mahasiswa": "49"
    },
    {
      "semester": "2022/2023 Ganjil",
      "jumlah_mahasiswa": "47"
    },
    {
      "semester": "2021/2022 Genap",
      "jumlah_mahasiswa": "43"
    },
    {
      "semester": "2021/2022 Ganjil",
      "jumlah_mahasiswa": "37"
    },
    {
      "semester": "2020/2021 Genap",
      "jumlah_mahasiswa": "34"
    },
    {
      "semester": "2020/2021 Ganjil",
      "jumlah_mahasiswa": "37"
    },
    {
      "semester": "2019/2020 Genap",
      "jumlah_mahasiswa": "37"
    },
    {
      "semester": "2019/2020 Ganjil",
      "jumlah_mahasiswa": "53"
    },
    {
      "semester": "2018/2019 Genap",
      "jumlah_mahasiswa": "47"
    }
  ],
  "kode_pt": "071024",
  "kode_ps": "54101",
  "nama_ps": "Agribisnis"
}